odoo/addons/energy_account_statement_import_file/README.md
odoo/addons/energy_account_statement_import_file/__init__.py
odoo/addons/energy_account_statement_import_file/__manifest__.py
odoo/addons/energy_account_statement_import_file/tests/TT290825.293 half day 1d2.txt
odoo/addons/energy_account_statement_import_file/tests/TT290825.741 full last day 2d2.txt
odoo/addons/energy_account_statement_import_file/tests/__init__.py
odoo/addons/energy_account_statement_import_file/tests/test_account_statement_import.py
odoo/addons/energy_account_statement_import_file/wizard/__init__.py
odoo/addons/energy_account_statement_import_file/wizard/account_statement_import.py
odoo_addon_energy_account_statement_import_file-16.0.0.1.1.dist-info/METADATA
odoo_addon_energy_account_statement_import_file-16.0.0.1.1.dist-info/WHEEL
odoo_addon_energy_account_statement_import_file-16.0.0.1.1.dist-info/top_level.txt
odoo_addon_energy_account_statement_import_file-16.0.0.1.1.dist-info/RECORD
