Metadata-Version: 2.1
Name: odoo-addon-energy_account_statement_import_file
Version: 16.0.0.1.1
Requires-Python: >=3.10
Requires-Dist: odoo-addon-account_statement_import_file>=16.0dev,<16.1dev
Requires-Dist: odoo>=16.0a,<16.1dev
Summary: Energy Import Statement Files
Home-page: https://git.coopdevs.org/coopdevs/comunitats-energetiques/odoo-ce
License: AGPL-3
Author: Coopdevs Treball SCCL & Som Energia SCCL
Classifier: Programming Language :: Python
Classifier: Framework :: Odoo
Classifier: Framework :: Odoo :: 16.0
Classifier: License :: OSI Approved :: GNU Affero General Public License v3
